pixelith/__init__.py
pixelith/core.py
pixelith-1.0.0.dist-info/licenses/LICENSE
pixelith-1.0.0.dist-info/METADATA
pixelith-1.0.0.dist-info/WHEEL
pixelith-1.0.0.dist-info/top_level.txt
pixelith-1.0.0.dist-info/RECORD
