Metadata-Version: 2.4
Name: pixelith
Version: 1.0.0
Summary: A Lightweight Multi-Tool Utility Library for Python.
Author-email: Salih Şimşek <salihsimsekhp@gmail.com>
License: MIT
Project-URL: Homepage, https://github.com/Neighboth
Requires-Python: >=3.8
License-File: LICENSE
Dynamic: license-file
